incolume/py/changelog/__init__.py
incolume/py/changelog/changelog.py
incolume/py/changelog/cli.py
incolume/py/changelog/version.txt
incolume_py_changelog-0.14.0.dist-info/METADATA
incolume_py_changelog-0.14.0.dist-info/WHEEL
incolume_py_changelog-0.14.0.dist-info/entry_points.txt
incolume_py_changelog-0.14.0.dist-info/RECORD
