Metadata-Version: 2.3
Name: incolume.py.changelog
Version: 0.14.0
Summary: Generate CHANGELOG.md
License: Unlicense
Keywords: python,utils,incolume
Author: britodfbr
Author-email: contato@incolume.com.br
Maintainer: britodfbr
Maintainer-email: contato@incolume.com.br
Requires-Python: >=3.8.1,<4.0.0
Classifier: Development Status :: 5 - Production/Stable
Classifier: License :: OSI Approved
Classifier: Natural Language :: Portuguese (Brazilian)
Classifier: Operating System :: OS Independent
Classifier: Programming Language :: Python
Classifier: Programming Language :: Python :: 3
Classifier: Programming Language :: Python :: 3.9
Classifier: Programming Language :: Python :: 3.10
Classifier: Programming Language :: Python :: 3.11
Classifier: Programming Language :: Python :: 3.12
Classifier: Programming Language :: Python :: 3.13
Classifier: Programming Language :: Python :: 3 :: Only
Classifier: Programming Language :: Python :: 3.8
Classifier: Topic :: Software Development :: Build Tools
Classifier: Topic :: Software Development :: Libraries :: Python Modules
Classifier: Topic :: Utilities
Requires-Dist: click (>=8.1.5,<9.0.0)
Requires-Dist: gitpython (>=3.1.43,<4.0.0)
Requires-Dist: toml[tomli] (>=0.10.2,<0.11.0)
Project-URL: Documentation, https://development-incolume.github.io/incolume.py.changelog/
Project-URL: Git, https://github.com/development-incolume/incolume.py.changelog.git
Project-URL: Homepage, https://pypi.org/project/incolume.py.changelog/
Project-URL: Oficial, https://pypi.org/project/incolume.py.changelog/
Project-URL: Repository, https://github.com/development-incolume/incolume.py.changelog.git
Project-URL: Source, https://github.com/development-incolume/incolume.py.changelog/releases
Project-URL: Tracker, https://github.com/development-incolume/incolume.py.changelog/issues
